CtfWriteups2016929/README.md
CtfWriteups2016929/__init__.py
CtfWriteups2016929/__main__.py
CtfWriteups2016929/file.epub
CtfWriteups2016929/index.html
CtfWriteups2016929/css/__init__.py
CtfWriteups2016929/css/annotations.css
CtfWriteups2016929/css/main.css
CtfWriteups2016929/css/normalize.css
CtfWriteups2016929/css/popup.css
CtfWriteups2016929/font/__init__.py
CtfWriteups2016929/font/fontello.eot
CtfWriteups2016929/font/fontello.svg
CtfWriteups2016929/font/fontello.ttf
CtfWriteups2016929/font/fontello.woff
CtfWriteups2016929/img/__init__.py
CtfWriteups2016929/img/annotator-glyph-sprite.png
CtfWriteups2016929/img/annotator-icon-sprite.png
CtfWriteups2016929/img/apple-touch-icon.png
CtfWriteups2016929/img/cancelfullscreen.png
CtfWriteups2016929/img/close.png
CtfWriteups2016929/img/fullscreen.png
CtfWriteups2016929/img/loader.gif
CtfWriteups2016929/img/menu-icon.png
CtfWriteups2016929/img/save.png
CtfWriteups2016929/img/saved.png
CtfWriteups2016929/img/settings-s.png
CtfWriteups2016929/img/settings.png
CtfWriteups2016929/img/star.png
CtfWriteups2016929/js/__init__.py
CtfWriteups2016929/js/epub.js
CtfWriteups2016929/js/epub.min.js
CtfWriteups2016929/js/epub.min.map
CtfWriteups2016929/js/hooks.min.js
CtfWriteups2016929/js/hooks.min.map
CtfWriteups2016929/js/reader.js
CtfWriteups2016929/js/reader.js.map
CtfWriteups2016929/js/reader.min.js
CtfWriteups2016929/js/reader.min.map
CtfWriteups2016929/js/hooks/__init__.py
CtfWriteups2016929/js/hooks/extensions/__init__.py
CtfWriteups2016929/js/hooks/extensions/highlight.js
CtfWriteups2016929/js/libs/__init__.py
CtfWriteups2016929/js/libs/jquery.min.js
CtfWriteups2016929/js/libs/localforage.min.js
CtfWriteups2016929/js/libs/screenfull.js
CtfWriteups2016929/js/libs/screenfull.min.js
CtfWriteups2016929/js/libs/zip.min.js
CtfWriteups2016929/js/plugins/__init__.py
CtfWriteups2016929/js/plugins/hypothesis.js
CtfWriteups2016929/js/plugins/search.js
ctf_writeups_2016_9_29-2024.3.2.0.dist-info/METADATA
ctf_writeups_2016_9_29-2024.3.2.0.dist-info/WHEEL
ctf_writeups_2016_9_29-2024.3.2.0.dist-info/entry_points.txt
ctf_writeups_2016_9_29-2024.3.2.0.dist-info/top_level.txt
ctf_writeups_2016_9_29-2024.3.2.0.dist-info/RECORD
